{"total_stories":4161,"total_tags":25,"tags":[{"tag":"Programming","count":1065},{"tag":"AI","count":881},{"tag":"Security","count":534},{"tag":"Hardware","count":495},{"tag":"Open Source","count":439},{"tag":"Science","count":421},{"tag":"Politics","count":416},{"tag":"Privacy","count":361},{"tag":"Culture","count":343},{"tag":"Business","count":335},{"tag":"Show HN","count":332},{"tag":"Web","count":258},{"tag":"Data","count":234},{"tag":"Design","count":229},{"tag":"DevOps","count":221},{"tag":"Legal","count":173},{"tag":"Education","count":157},{"tag":"Energy","count":121},{"tag":"Finance","count":109},{"tag":"Health","count":101},{"tag":"Gaming","count":99},{"tag":"Startups","count":79},{"tag":"Space","count":68},{"tag":"Entertainment","count":60},{"tag":"Career","count":46}]}