{"total_stories":5534,"total_tags":25,"tags":[{"tag":"Programming","count":1381},{"tag":"AI","count":1184},{"tag":"Security","count":708},{"tag":"Hardware","count":639},{"tag":"Science","count":577},{"tag":"Open Source","count":571},{"tag":"Politics","count":537},{"tag":"Privacy","count":493},{"tag":"Culture","count":463},{"tag":"Business","count":459},{"tag":"Show HN","count":416},{"tag":"Web","count":346},{"tag":"Design","count":312},{"tag":"Data","count":306},{"tag":"DevOps","count":287},{"tag":"Legal","count":219},{"tag":"Education","count":209},{"tag":"Energy","count":172},{"tag":"Health","count":147},{"tag":"Finance","count":141},{"tag":"Gaming","count":134},{"tag":"Startups","count":101},{"tag":"Space","count":86},{"tag":"Entertainment","count":79},{"tag":"Career","count":67}]}