{"total_stories":8562,"total_tags":25,"tags":[{"tag":"Programming","count":2199},{"tag":"AI","count":1900},{"tag":"Security","count":1034},{"tag":"Hardware","count":1007},{"tag":"Science","count":937},{"tag":"Open Source","count":873},{"tag":"Politics","count":809},{"tag":"Privacy","count":750},{"tag":"Business","count":732},{"tag":"Culture","count":701},{"tag":"Show HN","count":605},{"tag":"Web","count":521},{"tag":"Design","count":471},{"tag":"Data","count":468},{"tag":"DevOps","count":437},{"tag":"Education","count":342},{"tag":"Legal","count":328},{"tag":"Energy","count":275},{"tag":"Health","count":245},{"tag":"Gaming","count":224},{"tag":"Finance","count":219},{"tag":"Startups","count":178},{"tag":"Space","count":133},{"tag":"Entertainment","count":119},{"tag":"Career","count":117}]}