{"total_stories":2580,"total_tags":25,"tags":[{"tag":"Programming","count":672},{"tag":"AI","count":568},{"tag":"Security","count":316},{"tag":"Open Source","count":284},{"tag":"Hardware","count":282},{"tag":"Politics","count":279},{"tag":"Science","count":260},{"tag":"Privacy","count":225},{"tag":"Business","count":219},{"tag":"Culture","count":213},{"tag":"Show HN","count":210},{"tag":"Web","count":165},{"tag":"Data","count":155},{"tag":"Design","count":145},{"tag":"DevOps","count":130},{"tag":"Legal","count":107},{"tag":"Education","count":95},{"tag":"Energy","count":72},{"tag":"Health","count":64},{"tag":"Gaming","count":60},{"tag":"Finance","count":60},{"tag":"Startups","count":53},{"tag":"Entertainment","count":39},{"tag":"Space","count":26},{"tag":"Career","count":25}]}