{"total_stories":4667,"total_tags":25,"tags":[{"tag":"Programming","count":1185},{"tag":"AI","count":1010},{"tag":"Security","count":594},{"tag":"Hardware","count":549},{"tag":"Open Source","count":487},{"tag":"Science","count":485},{"tag":"Politics","count":463},{"tag":"Privacy","count":412},{"tag":"Culture","count":399},{"tag":"Business","count":387},{"tag":"Show HN","count":362},{"tag":"Web","count":288},{"tag":"Design","count":261},{"tag":"Data","count":260},{"tag":"DevOps","count":237},{"tag":"Legal","count":185},{"tag":"Education","count":172},{"tag":"Energy","count":135},{"tag":"Health","count":122},{"tag":"Finance","count":118},{"tag":"Gaming","count":115},{"tag":"Startups","count":86},{"tag":"Space","count":76},{"tag":"Entertainment","count":66},{"tag":"Career","count":52}]}